MANIFEST.in
setup.cfg
setup.py
django_iprestrict_proxytrust.egg-info/PKG-INFO
django_iprestrict_proxytrust.egg-info/SOURCES.txt
django_iprestrict_proxytrust.egg-info/dependency_links.txt
django_iprestrict_proxytrust.egg-info/not-zip-safe
django_iprestrict_proxytrust.egg-info/requires.txt
django_iprestrict_proxytrust.egg-info/top_level.txt
docs/Makefile
docs/changing_and_reloading_rules.rst
docs/conf.py
docs/configuration.rst
docs/index.rst
docs/installation.rst
iprestrict/__init__.py
iprestrict/admin.py
iprestrict/decorators.py
iprestrict/geoip.py
iprestrict/ip_utils.py
iprestrict/middleware.py
iprestrict/models.py
iprestrict/restrictor.py
iprestrict/urls.py
iprestrict/views.py
iprestrict/management/__init__.py
iprestrict/management/commands/__init__.py
iprestrict/management/commands/_utils.py
iprestrict/management/commands/add_ip_to_group.py
iprestrict/management/commands/import_rules.py
iprestrict/management/commands/importrules.py
iprestrict/management/commands/reload_rules.py
iprestrict/management/commands/reloadrules.py
iprestrict/migrations/0001_initial.py
iprestrict/migrations/0002_initial_data.py
iprestrict/migrations/0003_add_ipgroup_types.py
iprestrict/migrations/0004_add_iplocation.py
iprestrict/migrations/0005_add_reverse_ipgroup.py
iprestrict/migrations/0006_auto_20161013_1327.py
iprestrict/migrations/__init__.py