Metadata-Version: 1.1
Name: django-iprestrict-proxytrust
Version: 1.3.2
Summary: Django app + middleware to restrict access to all or sections of a Django project by client IP ranges
Home-page: https://github.com/metricmike/django-iprestrict
Author: Tamas Szabo, CCG, Murdoch University; Michael Weigle
Author-email: devops@ccg.murdoch.edu.au; michael.weigle@gmail.com
License: UNKNOWN
Download-URL: https://github.com/metricmike/django-iprestrict/releases
Platform: UNKNOWN
Classifier: Framework :: Django
Classifier: Intended Audience :: Developers
Classifier: License :: OSI Approved :: MIT License
Classifier: Operating System :: OS Independent
Classifier: Topic :: Software Development
